BlobDescription.py
PyblobLogger.py
PyblobLogging.py
AzurePyblobLogging-1.1.14.dist-info/LICENSE
AzurePyblobLogging-1.1.14.dist-info/METADATA
AzurePyblobLogging-1.1.14.dist-info/WHEEL
AzurePyblobLogging-1.1.14.dist-info/top_level.txt
AzurePyblobLogging-1.1.14.dist-info/RECORD
